reportwriter/__init__.py
reportwriter/__init__.pyi
reportwriter/py.typed
ReportWriter-0.0.11.dist-info/LICENSE
ReportWriter-0.0.11.dist-info/METADATA
ReportWriter-0.0.11.dist-info/WHEEL
ReportWriter-0.0.11.dist-info/top_level.txt
ReportWriter-0.0.11.dist-info/RECORD
