Metadata-Version: 2.1
Name: ReportWriter
Version: 0.0.11
Summary: A small class for building complex strings.
Home-page: https://github.com/benjaminsaljooghi/reportwriter
Author: Benjamin Saljooghi
Author-email: benjamin.saljooghi@gmail.com
License: UNKNOWN
Platform: UNKNOWN
Classifier: Programming Language :: Python :: 3
Classifier: License :: OSI Approved :: MIT License
Classifier: Operating System :: OS Independent
Requires-Python: >=3.7
